sphinxcontrib_dotnetdomain-0.4-py2.7-nspkg.pth
sphinxcontrib/dotnetdomain.py
sphinxcontrib_dotnetdomain-0.4.dist-info/DESCRIPTION.rst
sphinxcontrib_dotnetdomain-0.4.dist-info/METADATA
sphinxcontrib_dotnetdomain-0.4.dist-info/metadata.json
sphinxcontrib_dotnetdomain-0.4.dist-info/namespace_packages.txt
sphinxcontrib_dotnetdomain-0.4.dist-info/RECORD
sphinxcontrib_dotnetdomain-0.4.dist-info/top_level.txt
sphinxcontrib_dotnetdomain-0.4.dist-info/WHEEL
