Metadata-Version: 2.0
Name: sphinxcontrib-dotnetdomain
Version: 0.4
Summary: Sphinx "dotnetdomain" extension
Home-page: http://github.com/rtfd/sphinxcontrib-dotnetdomain
Author: Anthony Johnson
Author-email: aj@ohess.org
License: MIT
Download-URL: http://pypi.python.org/pypi/sphinxcontrib-dotnetdomain
Platform: any
Classifier: Development Status :: 2 - Pre-Alpha
Classifier: Environment :: Console
Classifier: Environment :: Web Environment
Classifier: Intended Audience :: Developers
Classifier: License :: OSI Approved :: MIT License
Classifier: Operating System :: OS Independent
Classifier: Programming Language :: Python
Classifier: Topic :: Documentation
Classifier: Topic :: Utilities
Requires-Dist: Sphinx (>=0.6)
